{
	"ABI version": 2,
	"header": ["time", "expire"],
	"functions": [
		{
			"name": "constructor",
			"inputs": [
				{"name":"relayKey","type":"uint256"}
			],
			"outputs": [
			]
		},
		{
			"name": "confirm",
			"inputs": [
				{"name":"relayKey","type":"uint256"}
			],
			"outputs": [
			]
		},
		{
			"name": "reject",
			"inputs": [
				{"name":"relayKey","type":"uint256"}
			],
			"outputs": [
			]
		},
		{
			"name": "getDetails",
			"inputs": [
			],
			"outputs": [
				{"components":[{"name":"eventTransaction","type":"uint256"},{"name":"eventIndex","type":"uint256"},{"name":"eventData","type":"cell"},{"name":"eventBlockNumber","type":"uint256"},{"name":"eventBlock","type":"uint256"},{"name":"ethereumEventConfiguration","type":"address"},{"name":"requiredConfirmations","type":"uint256"},{"name":"requiredRejects","type":"uint256"},{"name":"proxyAddress","type":"address"}],"name":"_initData","type":"tuple"},
				{"name":"_status","type":"uint8"},
				{"name":"_confirmKeys","type":"uint256[]"},
				{"name":"_rejectKeys","type":"uint256[]"}
			]
		}
	],
	"data": [
		{"components":[{"name":"eventTransaction","type":"uint256"},{"name":"eventIndex","type":"uint256"},{"name":"eventData","type":"cell"},{"name":"eventBlockNumber","type":"uint256"},{"name":"eventBlock","type":"uint256"},{"name":"ethereumEventConfiguration","type":"address"},{"name":"requiredConfirmations","type":"uint256"},{"name":"requiredRejects","type":"uint256"},{"name":"proxyAddress","type":"address"}],"key":1,"name":"initData","type":"tuple"}
	],
	"events": [
	]
}
